riffle/__init__.py
riffle/_version.py
riffle/browser.py
riffle/icon_factory.py
riffle/model.py
riffle/resource.py
Riffle-2.0.0.dist-info/LICENSE.txt
Riffle-2.0.0.dist-info/METADATA
Riffle-2.0.0.dist-info/WHEEL
Riffle-2.0.0.dist-info/top_level.txt
Riffle-2.0.0.dist-info/RECORD
