Metadata-Version: 2.1
Name: Riffle
Version: 2.0.0
Summary: Filesystem browser for PySide.
Home-page: https://gitlab.com/4degrees/riffle
Author: Martin Pengelly-Phillips
Author-email: martin@4degrees.ltd.uk
License: Apache License (2.0)
Keywords: filesystem,browser,pyside,qt,pyqt
Platform: UNKNOWN
Classifier: License :: OSI Approved :: Apache Software License
Classifier: Intended Audience :: Developers
Classifier: Programming Language :: Python :: 3
Requires-Python: >=3.8, <3.13
License-File: LICENSE.txt
Requires-Dist: PySide6 <7,>=6
Requires-Dist: clique <3,>=1.6
Provides-Extra: dev
Requires-Dist: PySide6 <7,>=6 ; extra == 'dev'
Requires-Dist: sphinx <4,>=2 ; extra == 'dev'
Requires-Dist: sphinx-rtd-theme <1,>=0.1.6 ; extra == 'dev'
Requires-Dist: lowdown <1,>=0.2.0 ; extra == 'dev'
Requires-Dist: mock <3,>=2 ; extra == 'dev'
Requires-Dist: pytest <5,>=2.3.5 ; extra == 'dev'
Provides-Extra: setup
Requires-Dist: PySide6 <7,>=6 ; extra == 'setup'
Requires-Dist: sphinx <4,>=2 ; extra == 'setup'
Requires-Dist: sphinx-rtd-theme <1,>=0.1.6 ; extra == 'setup'
Requires-Dist: lowdown <1,>=0.2.0 ; extra == 'setup'
Requires-Dist: mock <3,>=2 ; extra == 'setup'
Provides-Extra: tests
Requires-Dist: pytest <5,>=2.3.5 ; extra == 'tests'
